pyfs_mina/__init__.py
pyfs_mina/mina.py
pyfs_mina-1.0.5.dist-info/METADATA
pyfs_mina-1.0.5.dist-info/WHEEL
pyfs_mina-1.0.5.dist-info/top_level.txt
pyfs_mina-1.0.5.dist-info/RECORD
